xlsx2html/__init__.py
xlsx2html/__main__.py
xlsx2html/compat.py
xlsx2html/core.py
xlsx2html/constants/__init__.py
xlsx2html/constants/border.py
xlsx2html/constants/builtin.py
xlsx2html/constants/locale_format.py
xlsx2html/format/__init__.py
xlsx2html/format/dt.py
xlsx2html/format/hyperlink.py
xlsx2html/format/locale.py
xlsx2html/format/number.py
xlsx2html/utils/__init__.py
xlsx2html/utils/cell.py
xlsx2html/utils/image.py
xlsx2html-0.6.1.dist-info/LICENSE
xlsx2html-0.6.1.dist-info/METADATA
xlsx2html-0.6.1.dist-info/WHEEL
xlsx2html-0.6.1.dist-info/top_level.txt
xlsx2html-0.6.1.dist-info/RECORD
