Metadata-Version: 2.1
Name: xlsx2html
Version: 0.6.1
Summary: A simple export from xlsx format to html tables with keep cell formatting
Home-page: https://github.com/Apkawa/xlsx2html
Author: Apkawa
Author-email: apkawa@gmail.com
License: MIT
Keywords: converter xlsx html
Classifier: Development Status :: 3 - Alpha
Classifier: Intended Audience :: Developers
Classifier: License :: OSI Approved :: MIT License
Classifier: Programming Language :: Python
Classifier: Programming Language :: Python :: 3
Classifier: Programming Language :: Python :: 3.7
Classifier: Programming Language :: Python :: 3.8
Classifier: Programming Language :: Python :: 3.9
Classifier: Programming Language :: Python :: 3.10
Classifier: Programming Language :: Python :: 3.11
Classifier: Programming Language :: Python :: 3.12
Classifier: Programming Language :: Python :: Implementation :: PyPy
Classifier: Topic :: Text Processing
Classifier: Topic :: Text Processing :: Markup :: HTML
Requires-Python: >=3.6, <4
License-File: LICENSE
